PaintmanToolkit/__init__.py
PaintmanToolkit/paintman_toolkit.py
Paintman_Toolkit-1.0.3.dist-info/METADATA
Paintman_Toolkit-1.0.3.dist-info/WHEEL
Paintman_Toolkit-1.0.3.dist-info/top_level.txt
Paintman_Toolkit-1.0.3.dist-info/RECORD
