Metadata-Version: 2.1
Name: Paintman-Toolkit
Version: 1.0.3
Summary: A toolkit for reading and generating Paintman related files for color management.
Home-page: https://github.com/ChenxingM/PaintmanToolkit
Author: Ma Chenxing
Author-email: tammcx@gmail.com
Classifier: Programming Language :: Python :: 3
Classifier: License :: OSI Approved :: MIT License
Classifier: Operating System :: OS Independent
Requires-Python: >=3.6
